{
  "base_resolution": [
    2592,
    1944
  ],
  "zones": [
    {
      "name": "a",
      "polygon": [
        [
          2.942731277533069,
          259.8590308370043
        ],
        [
          465.3920704845815,
          316.9515418502202
        ],
        [
          2152.916299559471,
          248.44052863436113
        ],
        [
          2469.779735682819,
          436.8458149779735
        ],
        [
          2586.819383259912,
          568.15859030837
        ],
        [
          2589.674008810573,
          956.8281938325993
        ],
        [
          0.08810572687223568,
          1170.9250888967692
        ]
      ]
    },
    {
      "name": "b",
      "polygon": [
        [
          100,
          100
        ],
        [
          2589.6740088105726,
          8.651982378854635
        ],
        [
          2586.8193832599122,
          551.4713656387665
        ],
        [
          2469.7797356828196,
          431.57709251101323
        ],
        [
          2152.9162995594716,
          246.0264317180617
        ],
        [
          448.26431718061673,
          314.53744493392065
        ],
        [
          54.3259911894273,
          260.2995594713656
        ]
      ]
    },
    {
      "name": "c",
      "polygon": [
        [
          2.9427312775330488,
          1179.0484581497797
        ],
        [
          2589.6740088105726,
          964.9515418502203
        ],
        [
          2586.819383259912,
          1938.819383259912
        ],
        [
          -2.766519823788557,
          1941.6740088105728
        ]
      ]
    }
  ]
}
